[
    {
        "_id": "00000000-0000-0000-0000-000000000001",
        "_name": "ФайлГид",
        "_icon": "apps-icons/file-guide.svg"
    },
    {
        "_id": "00000000-0000-0000-0000-000000000004",
        "_name": "Калькулятор",
        "_icon": "apps-icons/calculator.svg"
    },
    {
        "_id": "00000000-0000-0000-0000-000000000003",
        "_name": "Браузер",
        "_icon": "apps-icons/browser.svg"
    },
    {
        "_id": "00000000-0000-0000-0000-000000000002",
        "_name": "Корзина",
        "_icon": "apps-icons/delete-bin.svg"
    }
]